awslabs/__init__.py
awslabs/aws_iac_mcp_server/__init__.py
awslabs/aws_iac_mcp_server/config.py
awslabs/aws_iac_mcp_server/knowledge_models.py
awslabs/aws_iac_mcp_server/sanitizer.py
awslabs/aws_iac_mcp_server/server.py
awslabs/aws_iac_mcp_server/client/aws_client.py
awslabs/aws_iac_mcp_server/client/aws_knowledge_client.py
awslabs/aws_iac_mcp_server/client/mcp_proxy.py
awslabs/aws_iac_mcp_server/data/cloudformation_failure_cases.py
awslabs/aws_iac_mcp_server/data/default_guard_rules.guard
awslabs/aws_iac_mcp_server/tools/cdk_best_practices.py
awslabs/aws_iac_mcp_server/tools/cloudformation_compliance_checker.py
awslabs/aws_iac_mcp_server/tools/cloudformation_deployment_troubleshooter.py
awslabs/aws_iac_mcp_server/tools/cloudformation_pre_deploy_validation.py
awslabs/aws_iac_mcp_server/tools/cloudformation_validator.py
awslabs/aws_iac_mcp_server/tools/iac_tools.py
awslabs_aws_iac_mcp_server-1.0.10.dist-info/METADATA
awslabs_aws_iac_mcp_server-1.0.10.dist-info/WHEEL
awslabs_aws_iac_mcp_server-1.0.10.dist-info/entry_points.txt
awslabs_aws_iac_mcp_server-1.0.10.dist-info/licenses/LICENSE
awslabs_aws_iac_mcp_server-1.0.10.dist-info/licenses/NOTICE
awslabs_aws_iac_mcp_server-1.0.10.dist-info/RECORD
